.mica_settings
.project
.pydevproject
MANIFEST.in
ez_setup.py
setup.cfg
setup.py
hildon/gnatirac.desktop
hildon/icons/48x48/gnatirac.png
hildon/icons/64x64/gnatirac.png
media/gnatirac.png
scripts/gnatirac
src/gnatirac/__init__.py
src/gnatirac/bootstrap.py
src/gnatirac/gnatirac-logo.png
src/gnatirac.egg-info/PKG-INFO
src/gnatirac.egg-info/SOURCES.txt
src/gnatirac.egg-info/dependency_links.txt
src/gnatirac.egg-info/not-zip-safe
src/gnatirac.egg-info/requires.txt
src/gnatirac.egg-info/top_level.txt
src/gnatirac/common/__init__.py
src/gnatirac/common/version.py
src/gnatirac/core/__init__.py
src/gnatirac/core/exceptions.py
src/gnatirac/core/gnatirac.py
src/gnatirac/gui/__init__.py
src/gnatirac/gui/gtk/__init__.py
src/gnatirac/gui/gtk/utils.py
src/gnatirac/gui/gtk/widget.py
src/gnatirac/gui/hildon/__init__.py
src/gnatirac/gui/hildon/gnatiracGui.py
src/gnatirac/gui/hildon/portrait.py
src/gnatirac/gui/hildon/utils.py
src/gnatirac/gui/hildon/widget.py