Metadata-Version: 1.0
Name: gnatirac
Version: 0.1.0dev-r114
Summary: Gnatirac is a Picasa Web client for N900
Home-page: http://blog.gnatirac.bressure.net
Author: Thierry Bressure
Author-email: gnatirac@bressure.net
License: UNKNOWN
Download-URL: http://gnatirac.bressure.net
Platform: UNKNOWN
Classifier: Development Status :: 2 - Pre-Alpha
Classifier: Environment :: Handhelds/PDA's
Classifier: Intended Audience :: End Users/Desktop
Classifier: Intended Audience :: Developers
Classifier: License :: OSI Approved :: GNU Library or Lesser General Public License (LGPL)
Classifier: Operating System :: POSIX :: Linux
Classifier: Programming Language :: Python
